README.txt
setup.py
Products/__init__.py
Products.PloneQueueCatalog.egg-info/PKG-INFO
Products.PloneQueueCatalog.egg-info/SOURCES.txt
Products.PloneQueueCatalog.egg-info/dependency_links.txt
Products.PloneQueueCatalog.egg-info/namespace_packages.txt
Products.PloneQueueCatalog.egg-info/not-zip-safe
Products.PloneQueueCatalog.egg-info/requires.txt
Products.PloneQueueCatalog.egg-info/top_level.txt
Products/PloneQueueCatalog/QueueCatalogPatches.py
Products/PloneQueueCatalog/__init__.py
Products/PloneQueueCatalog/version.txt
Products/PloneQueueCatalog/Extensions/Install.py
Products/PloneQueueCatalog/Extensions/__init__.py
docs/HISTORY.txt
docs/INSTALL.txt
