Metadata-Version: 1.0
Name: Products.PloneQueueCatalog
Version: 2.0
Summary: Products.PloneQueueCatalog makes it easier to use QueueCatalog in your Plone site.
Home-page: http://svn.plone.org/svn/collective/PloneQueueCatalog/trunk
Author: Helge Tesdal
Author-email: plone-developers@lists.sourceforge.net
License: GPL
Keywords: Plone QueueCatalog
Platform: UNKNOWN
Classifier: Framework :: Plone
Classifier: Framework :: Zope2
Classifier: Programming Language :: Python
